Metadata-Version: 2.1
Name: sdmpm
Version: 0.1
Summary: SystemD multi-process manager
Home-page: https://github.com/anlutro/systemd-multi-process-manager
Author: Andreas Lutro
Author-email: anlutro@gmail.com
License: GPL-3.0
Platform: UNKNOWN
